eve/__init__.py
eve/app/__init__.py
eve/app/algo.py
eve/app/buffers.py
eve/app/callbacks.py
eve/app/env.py
eve/app/exp_manager.py
eve/app/hyperparams_opt.py
eve/app/logger.py
eve/app/model.py
eve/app/policies.py
eve/app/space.py
eve/app/trainer.py
eve/app/upgrader.py
eve/app/utils.py
eve/app/algorithm/__init__.py
eve/app/algorithm/a2c.py
eve/app/algorithm/ddpg.py
eve/app/algorithm/dqn.py
eve/app/algorithm/ppo.py
eve/app/algorithm/sac.py
eve/app/algorithm/td3.py
eve/core/__init__.py
eve/core/eve.py
eve/core/layer.py
eve/core/node.py
eve/core/prune.py
eve/core/quan.py
eve/core/quantize_fn.py
eve/core/state.py
eve/core/surrogate_fn.py
eve/utils/__init__.py
eve/utils/legacy.py
test/__init__.py
test/test_a2c.py
test/test_ddpg.py
test/test_dqn.py
test/test_eve.py
test/test_model.py
test/test_node.py
test/test_ppo.py
test/test_quan.py
test/test_sac.py
test/test_td3.py
test/utils.py
eve_mli-0.1.0.dist-info/LICENSE
eve_mli-0.1.0.dist-info/METADATA
eve_mli-0.1.0.dist-info/WHEEL
eve_mli-0.1.0.dist-info/top_level.txt
eve_mli-0.1.0.dist-info/RECORD
