Metadata-Version: 2.1
Name: eve-mli
Version: 0.1.0
Summary: eve-mli: making learning interesting.
Home-page: https://github.com/densechen/eve-mli
Author: densechen
Author-email: densechen@foxmail.com
License: MIT
Download-URL: https://github.com/densechen/eve-mli/archive/main.zip
Platform: UNKNOWN
Classifier: Programming Language :: Python :: 3 :: Only
Classifier: Operating System :: OS Independent
Requires-Python: >=3.6
Requires-Dist: cloudpickle
Requires-Dist: matplotlib
Requires-Dist: numpy
Requires-Dist: optuna
Requires-Dist: pandas
Requires-Dist: psutil
Requires-Dist: PyYAML
Requires-Dist: tensorboard
Requires-Dist: tensorboard-plugin-wit
Requires-Dist: torch (>=1.5.0)
Requires-Dist: torchvision
Requires-Dist: tqdm
